rtm/__init__.py
rtm/containers/field.py
rtm/containers/fields.py
rtm/containers/markup.py
rtm/containers/work_items.py
rtm/containers/worksheet_columns.py
rtm/main/api.py
rtm/main/cli.py
rtm/main/config.py
rtm/main/context_managers.py
rtm/main/excel.py
rtm/main/exceptions.py
rtm/main/versions.py
rtm/validate/checks.py
rtm/validate/validation.py
rtm/validate/validator_output.py
dps_rtm-0.1.27.dist-info/entry_points.txt
dps_rtm-0.1.27.dist-info/LICENSE
dps_rtm-0.1.27.dist-info/WHEEL
dps_rtm-0.1.27.dist-info/METADATA
dps_rtm-0.1.27.dist-info/RECORD
