Metadata-Version: 2.1
Name: dps-rtm
Version: 0.1.27
Summary: Validate a Requirements Trace Matrix
Home-page: https://github.com/jonathanchukinas/fdr
License: UNKNOWN
Author: Jonathan Chukinas
Author-email: chukinas@gmail.com
Requires-Python: >=3.6
Classifier: License :: OSI Approved :: MIT License
Requires-Dist: click
Requires-Dist: openpyxl
Requires-Dist: colorama
Requires-Dist: requests
